.gitignore
.gitlab-ci.yml
COPYING
Makefile
README.md
TODO
TODO.md
appveyor.yml
environment.yml
pyproject.toml
requirements.txt
setup.py
.idea/PyCommunication.iml
.idea/git_toolbox_prj.xml
.idea/misc.xml
.idea/modules.xml
.idea/other.xml
.idea/vcs.xml
.idea/inspectionProfiles/Project_Default.xml
Scripts/32_qam_equalisation.py
Scripts/64_qam_equalisation.py
Scripts/64qam_data_test.py
Scripts/ber_vs_evm.py
Scripts/ber_vs_evm_with_equalisation.py
Scripts/cma_equaliser.py
Scripts/mrde_equaliser.py
Scripts/mrde_equaliser_profiling.py
Scripts/phaserecoverytest.py
Scripts/pilot_tests.py
Scripts/profile_mrde.sh
Scripts/run_pilot.py
Scripts/sim_pilot_txrx.py
Scripts/Notebooks/Demo of Geometric shaping in transmitter model - pilot_based centering.ipynb
Scripts/Notebooks/Demo of Tx model with full compensation.ipynb
Scripts/Notebooks/Demo of transmitter distortion test .ipynb
Scripts/Notebooks/Demo of transmitter impairment simulation.ipynb
Scripts/Notebooks/Demo of transmitter impairment simulation_constant ASE noise model.ipynb
Scripts/Notebooks/Hackathon QAMpy QPSK demo.ipynb
Scripts/Notebooks/HackathonIntro.ipynb
Scripts/Notebooks/HackathonIntro_64QAM.ipynb
Scripts/Notebooks/Modulation Format Demo.ipynb
Scripts/Notebooks/PilotBasedDSP_SignalObjectDemo.ipynb
Scripts/Notebooks/QAMPy higher-order QAM.ipynb
Scripts/Notebooks/QPSK simulation.ipynb
Scripts/Notebooks/QPSK simulation_presentation.ipynb
Scripts/data/20GBaud_SRRC0P05_64QAM_PRBS15.mat
Scripts/data/OSNRLoading_1544p32_Att_2_OSNR_37_3.mat
Scripts/data/OSNRLoading_1546p31_Att_1_OSNR_37_1.mat
Scripts/data/OSNRLoading_IdealRxLaser_1544p91_Att_1_OSNR_38_1.mat
docs/conf.py
docs/index.md
docs/installation/index.md
docs/installation/linux.md
docs/installation/windows.md
docs/reference/index.md
docs/reference/basic/analog_frontend.rst
docs/reference/basic/equalisation.rst
docs/reference/basic/filtering.rst
docs/reference/basic/helpers.rst
docs/reference/basic/impairments.rst
docs/reference/basic/index.md
qampy.egg-info/PKG-INFO
qampy.egg-info/SOURCES.txt
qampy.egg-info/dependency_links.txt
qampy.egg-info/requires.txt
qampy.egg-info/top_level.txt
