Metadata-Version: 2.1
Name: qampy
Version: 0.5.0
Summary: A python based package of communications qampy tools
Author: Jochen Schröder, Mikael Mazur and Zonglong He
Author-email: Jochen Schröder <jochen.schroeder@chalmers.se>, Mikael Mazur <mik.mazur@gmail.com>, Zonglong He <zonglong.he@chalmers.se>
Maintainer-email: Jochen Schröder <jochen.schroeder@chalmers.se>
License: GPLv3
Project-URL: homepage, https://qampy.org
Project-URL: repository, https://github.com/ChalmersPhotonicsLab/QAMpy
Keywords: digital signal processing,communications,photonics,science
Classifier: Development Status :: 4 - Beta
Classifier: Intended Audience :: Developers
Classifier: Intended Audience :: Science/Research
Classifier: Topic :: Software Development :: Libraries
Classifier: Topic :: Scientific/Engineering
Classifier: Operating System :: Microsoft :: Windows
Classifier: Operating System :: POSIX :: Linux
Classifier: Operating System :: POSIX
Classifier: Operating System :: Unix
Classifier: Operating System :: MacOS
Classifier: License :: OSI Approved :: GNU General Public License v3 or later (GPLv3+)
Classifier: Programming Language :: Python :: 3
Classifier: Programming Language :: Python :: 3.7
Classifier: Programming Language :: Python :: 3.8
Classifier: Programming Language :: Python :: 3.9
Classifier: Programming Language :: Python :: 3.10
Requires-Python: >=3.7
Provides-Extra: test
Provides-Extra: docs
